deap/__init__.py
deap/algorithms.py
deap/base.py
deap/cma.py
deap/creator.py
deap/gp.py
deap/benchmarks/__init__.py
deap/benchmarks/binary.py
deap/benchmarks/gp.py
deap/benchmarks/movingpeaks.py
deap/benchmarks/tools.py
deap/tools/__init__.py
deap/tools/constraint.py
deap/tools/crossover.py
deap/tools/emo.py
deap/tools/indicator.py
deap/tools/init.py
deap/tools/migration.py
deap/tools/mutation.py
deap/tools/selection.py
deap/tools/support.py
deap/tools/_hypervolume/__init__.py
deap/tools/_hypervolume/hv.cpython-313-aarch64-linux-gnu.so
deap/tools/_hypervolume/pyhv.py
deap-1.4.3.dist-info/METADATA
deap-1.4.3.dist-info/WHEEL
deap-1.4.3.dist-info/top_level.txt
deap-1.4.3.dist-info/RECORD
deap-1.4.3.dist-info/licenses/LICENSE.txt
